[
    {
        "id": 0, 
        "title": "WDW魔法王国", 
        "image": "https://xforgeassets002.xboxlive.com/pf-title-b63a0803d3653643-20ca2/8ddd0f7c-d6a9-45a6-b708-a7575b8c070e/WDW-Magic-Kingdom-Adventure_thumbnail_0.jpg", 
        "description": "重现原汁原味的华特迪士尼世界魔法王国！体验备受欢迎的景点，与迪士尼和 Pixar 的经典角色见面，欣赏壮观的焰火表演，欢庆华特迪士尼世界 50 周年。包括 25 款皮肤和特殊的游戏内商品，您可以潇洒地参加庆祝活动", 
        "rating": 4.7, 
        "minecoin": "1340",
        "author": "Fanconma",
        "studio": "Everbloom Games",
        "url": "https://pan.baidu.com/s/1q_znLj-QeIkj85Ai_sGDug?pwd=qkbb",
        "tags": ["Disney", "迪士尼"],
        "name-eng": "WDW Magic Kingdom",
        "official": true,
        "best_quality": true
    },
    {
        "id": 1, 
        "title": "200个生物", 
        "image": "https://xforgeassets002.xboxlive.com/pf-namespace-b63a0803d3653643/46f4bb93-3080-4bc7-888e-652459ac4331/Caves__Cliffs_Explorers_Thumbnail_0.jpg", 
        "description": "《我的世界》市场的创作者 Spark Universe 为您奉上洞穴及悬崖探索者地图。通过有趣的任务和轻松的游戏来重建并发展一个破败的村庄，从而了解这次更新的内容！", 
        "rating": "4.5", 
        "minecoin": "0",
        "author": "Fanconma",
        "studio": "Spark Universe",
        "url": "https://pan.baidu.com/s/1cWpAHuxMOL9BKg2sB0Gv7Q?pwd=tef6",
        "tags": ["1.20", "洞穴与山崖"],
        "name-eng": "Caves & Cliffs Explorers",
        "official": false,
        "best-quality": false
    },
    {
        "id": 2, 
        "title": "愤怒的小鸟", 
        "image": "https://xforgeassets002.xboxlive.com/pf-namespace-b63a0803d3653643/f705f9ed-f150-4259-956c-64a19a56a68a/angrybirds_Thumbnail_0.jpg", 
        "description": "捣蛋猪又玩它们的老把戏，这一次您一定要阻止它们！扮演胖红、飞镖黄、炸弹黑以及其他小鸟，您的任务是拯救自己的朋友，拯救鸟蛋，阻止捣蛋猪的大计划。每救一只小鸟，您就能解锁新的可玩角色，新角色都有独特技能，能帮您制服更多捣蛋猪，撞翻更多高塔！", 
        "rating": "4.6", 
        "minecoin": "1340",
        "author": "Fanconma",
        "studio": "Oreville Studios",
        "url": "https://pan.baidu.com/s/1eNTyCLV4_tk9SRM7e_TxJQ?pwd=2ux8",
        "name-eng": "Caves & Cliffs Explorers",
        "official": true,
        "best-quality": false
    }
]